{"Nodes":[],"ExecutionTime":"2023-04-25T18:17:54.2922826Z","GenerationTime":"0001-01-01T00:00:00","PluginUserSpecFlowId":"45291d50-88fc-4e5d-ae85-de5aaa676942","CLIUserSpecFlowId":null,"ExecutionResults":[{"ContextType":"Scenario","FeatureFolderPath":"Features","FeatureTitle":"LoginTest","ScenarioTitle":"Login Test to ACUK website","ScenarioArguments":[],"Status":"UndefinedStep","StepResults":[{"Duration":null,"Status":"UndefinedStep","Error":null,"Outputs":null},{"Duration":null,"Status":"UndefinedStep","Error":null,"Outputs":null},{"Duration":null,"Status":"UndefinedStep","Error":null,"Outputs":null},{"Duration":null,"Status":"UndefinedStep","Error":null,"Outputs":null},{"Duration":null,"Status":"UndefinedStep","Error":null,"Outputs":null},{"Duration":null,"Status":"UndefinedStep","Error":null,"Outputs":null},{"Duration":null,"Status":"UndefinedStep","Error":null,"Outputs":null},{"Duration":null,"Status":"UndefinedStep","Error":null,"Outputs":null},{"Duration":null,"Status":"UndefinedStep","Error":null,"Outputs":null},{"Duration":null,"Status":"UndefinedStep","Error":null,"Outputs":null}],"Outputs":null}],"StepReports":null}